xaws/__init__.py
xaws/command.py
xaws/kms.py
xaws-1.0.2.dist-info/METADATA
xaws-1.0.2.dist-info/WHEEL
xaws-1.0.2.dist-info/entry_points.txt
xaws-1.0.2.dist-info/RECORD
